odoo/addons/fleet_vehicle_log_fuel/README.rst
odoo/addons/fleet_vehicle_log_fuel/__init__.py
odoo/addons/fleet_vehicle_log_fuel/__manifest__.py
odoo/addons/fleet_vehicle_log_fuel/i18n/es.po
odoo/addons/fleet_vehicle_log_fuel/i18n/fleet_vehicle_log_fuel.pot
odoo/addons/fleet_vehicle_log_fuel/i18n/it.po
odoo/addons/fleet_vehicle_log_fuel/i18n/pt_BR.po
odoo/addons/fleet_vehicle_log_fuel/migrations/14.0.1.0.0/post-migration.py
odoo/addons/fleet_vehicle_log_fuel/models/__init__.py
odoo/addons/fleet_vehicle_log_fuel/models/fleet_vehicle.py
odoo/addons/fleet_vehicle_log_fuel/models/fleet_vehicle_log_fuel.py
odoo/addons/fleet_vehicle_log_fuel/readme/CONTRIBUTORS.rst
odoo/addons/fleet_vehicle_log_fuel/readme/DESCRIPTION.rst
odoo/addons/fleet_vehicle_log_fuel/report/__init__.py
odoo/addons/fleet_vehicle_log_fuel/report/fleet_report.py
odoo/addons/fleet_vehicle_log_fuel/security/fleet_security.xml
odoo/addons/fleet_vehicle_log_fuel/security/ir.model.access.csv
odoo/addons/fleet_vehicle_log_fuel/static/description/icon.png
odoo/addons/fleet_vehicle_log_fuel/static/description/index.html
odoo/addons/fleet_vehicle_log_fuel/views/fleet_board_view.xml
odoo/addons/fleet_vehicle_log_fuel/views/fleet_vehicle_cost_views.xml
odoo/addons/fleet_vehicle_log_fuel/views/fleet_vehicle_views.xml
odoo14_addon_fleet_vehicle_log_fuel-14.0.2.0.0.dist-info/METADATA
odoo14_addon_fleet_vehicle_log_fuel-14.0.2.0.0.dist-info/WHEEL
odoo14_addon_fleet_vehicle_log_fuel-14.0.2.0.0.dist-info/top_level.txt
odoo14_addon_fleet_vehicle_log_fuel-14.0.2.0.0.dist-info/RECORD
